{
    "keep": {
        "days": true,
        "amount": 14
    },
    "auditLog": "C:\\Users\\JSK\\Downloads\\Studioinfinito-main\\Studioinfinito-main\\backend\\logs\\.ee2992a97f04d8ffd3097e4d76cfa83103912a72-audit.json",
    "files": [
        {
            "date": 1778009183777,
            "name": "C:\\Users\\JSK\\Downloads\\Studioinfinito-main\\Studioinfinito-main\\backend\\logs\\combined-2026-05-06.log",
            "hash": "c26026b29defcddb49532689a77bf16dbf9e2c7d281ac673eae849d6563189f7"
        }
    ],
    "hashType": "sha256"
}